source/dsp/multiplier/multiplier.vhd
library ieee;
    use ieee.std_logic_1164.all;
    use ieee.numeric_std.all;

library work;
    use work.multiplier_pkg.all;

entity multiplier is
    port (
        multiplier_clocks : in multiplier_clock_group;

        multiplier_data_in : in multiplier_data_input_group;
        multiplier_data_out : out multiplier_data_output_group
    );
end entity;

architecture rtl of multiplier is


    signal mult_result : result_array(0 to 1);
    signal mult_a, mult_b : sign_array(0 to 1);

begin

    test_multiplier : process(multiplier_clocks.dsp_clock)

        variable multiplier_counter : integer range 0 to 7; 
    begin
        if rising_edge(multiplier_clocks.dsp_clock) then

            mult_a(0) <= to_signed(multiplier_data_in.mult_a,18);
            mult_b(0) <= to_signed(multiplier_data_in.mult_b,18);
            mult_a(1) <= mult_a(0);
            mult_b(1) <= mult_b(0);
            mult_result(0) <= mult_a(0) * mult_b(0);
            mult_result(1) <= mult_result(0);

            multiplier_data_out.multiplier_result <= mult_result(0);

            multiplier_data_out.multiplier_is_ready <= false;
            CASE multiplier_counter is
                WHEN 0 =>
                    if multiplier_data_in.multiplication_is_requested then
                        multiplier_counter := multiplier_counter + 1;
                    end if;
                WHEN 1 => 
                    multiplier_counter := multiplier_counter + 1;
                WHEN 2 => 
                    multiplier_data_out.multiplier_is_ready <= true;
                    multiplier_counter := 0;
                WHEN others =>
                    multiplier_counter := 0;
            end CASE;
        end if; --rising_edge
    end process test_multiplier;	

end rtl;

source/dsp/multiplier/simulation/tb_multiplier.vhd
LIBRARY ieee  ; 
LIBRARY std  ; 
    USE ieee.NUMERIC_STD.all  ; 
    USE ieee.std_logic_1164.all  ; 
    USE ieee.std_logic_textio.all  ; 
    use ieee.math_real.all;
    USE std.textio.all  ; 

library work;
    use work.multiplier_pkg.all;

entity tb_multiplier is
end;

architecture sim of tb_multiplier is
    signal rstn : std_logic;

    signal simulation_running : boolean;
    signal simulator_clock : std_logic;
    constant clock_per : time := 1 ns;
    constant clock_half_per : time := 0.5 ns;
    constant simtime_in_clocks : integer := 200;

    signal multiplier_clocks   : multiplier_clock_group;
    signal multiplier_data_in  : multiplier_data_input_group;
    signal multiplier_data_out :  multiplier_data_output_group;
    signal mpy_test : sign36;
    signal testcounter : integer;
    signal signal_counter : int18;
    signal jihuu_y : int18;

------------------------------------------------------------------------
    procedure pi_control
    (
        variable uin, y, mem, radix, process_counter : inout int18;
        constant b0, b1 : int18;
        signal alu_in : out multiplier_data_input_group;
        signal alu_out : in multiplier_data_output_group
    ) is
    begin
        CASE process_counter is
           WHEN 0 => 
                alu_mpy(uin, b0, alu_in);
                increment(process_counter);
            WHEN 1 => 
                alu_mpy(uin, b1, alu_in);
                increment(process_counter);
            WHEN 2 => 
                increment(process_counter);
                y := mem + get_result(alu_out,radix);
                if y >= 2**15 then
                    y := 2**15;
                    mem :=  2**15-get_result(alu_out,radix);
                    process_counter := 0;
                end if;

                if y <= -2**15 then
                    y := -2**15;
                    mem := -2**15-get_result(alu_out,radix);
                    process_counter := 0;
                end if; 
            WHEN 3 =>
                mem := mem + get_result(alu_out,radix);
                process_counter := 0;
            WHEN others =>
                process_counter := 0;
        end CASE;
    end pi_control;
------------------------------------------------------------------------

begin

    simtime : process
    begin
            simulation_running <= true;
        wait for simtime_in_clocks*clock_per;
            simulation_running <= false;
        wait;
    end process simtime;	


    sim_clock_gen : process
    begin
        simulator_clock <= '0';
        rstn <= '0';
        simulator_clock <= '0';
        wait for clock_half_per;
        while simulation_running loop
            wait for clock_half_per;
                rstn <= '1';
                simulator_clock <= not simulator_clock;
            end loop;
        wait;
    end process;
------------------------------------------------------------------------
    multiplier_clocks.dsp_clock <= simulator_clock;
    u_multiplier : multiplier
        port map(
            multiplier_clocks, 
            multiplier_data_in,
            multiplier_data_out 
        );
------------------------------------------------------------------------
    test_multiplier : process(simulator_clock, rstn)

        constant b1 : int18 := 7800;
        constant a1 : int18 := 11e3;
        constant b0 : int18 := 2**15-a1-b1;
        variable uin : int18 := -10e3;
        variable mem1, mem2, y : int18;
        variable a, b: int18;
        variable mpy_result : sign36;
        variable process_counter : int18;
        variable plaaplaa :int18;
        variable radix : int18;
        ------------------------------------------------------------------------
        impure function "*" (left, right : int18) return int18
        is
            variable result : sign36;
        begin
            alu_mpy(left, right, multiplier_data_in, multiplier_data_out);
            return get_result(multiplier_data_out,radix);
        end "*";
        ------------------------------------------------------------------------
    begin
        if rstn = '0' then
        -- reset state
            a := 16;
            b := 16;
            mpy_test <= (others => '0');
            process_counter := 0;
            mem1 := 0;
            y := 0;
            signal_counter <= process_counter;
            process_counter := 0;
            jihuu_y <= 0;
            radix := 0;

        elsif rising_edge(simulator_clock) then
            signal_counter <= process_counter;
            testcounter <= process_counter;
            mpy_test <=multiplier_data_out.multiplier_result; 
            jihuu_y <= y;

            radix := 14;
            pi_control(uin,y,mem1,radix,process_counter,b0,b1,multiplier_data_in,multiplier_data_out); 

        end if; -- rstn
    end process test_multiplier;	

end sim;

source/dsp/multiplier/simulation/tb_multiplier.vcd
$date
  Fri Jan 17 22:05:22 2020
$end
$version
  GHDL v0
$end
$timescale
  1 fs
$end
$scope module standard $end
$upscope $end
$scope module textio $end
$upscope $end
$scope module std_logic_1164 $end
$upscope $end
$scope module numeric_std $end
$upscope $end
$scope module std_logic_textio $end
$upscope $end
$scope module math_real $end
$upscope $end
$scope module multiplier_pkg $end
$upscope $end
$scope module tb_multiplier $end
$var reg 1 ! rstn $end
$var reg 1 " simulation_running $end
$var reg 1 # simulator_clock $end
$comment multiplier_clocks is not handled $end
$comment multiplier_data_in is not handled $end
$comment multiplier_data_out is not handled $end
$var reg 36 $ mpy_test[35:0] $end
$var integer 32 % testcounter $end
$scope module u_multiplier $end
$comment multiplier_clocks is not handled $end
$comment multiplier_data_in is not handled $end
$comment multiplier_data_out is not handled $end
$comment mult_result is not handled $end
$comment mult_a is not handled $end
$comment mult_b is not handled $end
$upscope $end
$upscope $end
$enddefinitions $end
#0
0!
1"
0#
b000000000000000000000000000000000000 $
b10000000000000000000000000000000 %
#500000
#1000000
1!
1#
bUUUUUUUUUUUUUUUUUUUUUUUUUUUUUUUUUUUU $
b0 %
#1500000
0#
#2000000
1#
#2500000
0#
#3000000
1#
bXXXXXXXXXXXXXXXXXXXXXXXXXXXXXXXXXXXX $
#3500000
0#
#4000000
1#
b000000000000000000000000000100000000 $
b1 %
#4500000
0#
#5000000
1#
#5500000
0#
#6000000
1#
#6500000
0#
#7000000
1#
#7500000
0#
#8000000
1#
b10 %
#8500000
0#
#9000000
1#
#9500000
0#
#10000000
1#
#10500000
0#
#11000000
1#
#11500000
0#
#12000000
1#
b11 %
#12500000
0#
#13000000
1#
#13500000
0#
#14000000
1#
#14500000
0#
#15000000
1#
#15500000
0#
#16000000
1#
b100 %
#16500000
0#
#17000000
1#
#17500000
0#
#18000000
1#
#18500000
0#
#19000000
1#
#19500000
0#
#20000000
1#
b101 %
#20500000
0#
#21000000
1#
#21500000
0#
#22000000
1#
#22500000
0#
#23000000
1#
#23500000
0#
#24000000
1#
b110 %
#24500000
0#
#25000000
1#
#25500000
0#
#26000000
1#
#26500000
0#
#27000000
1#
#27500000
0#
#28000000
1#
b111 %
#28500000
0#
#29000000
1#
#29500000
0#
#30000000
1#
#30500000
0#
#31000000
1#
#31500000
0#
#32000000
1#
b1000 %
#32500000
0#
#33000000
1#
#33500000
0#
#34000000
1#
#34500000
0#
#35000000
1#
#35500000
0#
#36000000
1#
b1001 %
#36500000
0#
#37000000
1#
#37500000
0#
#38000000
1#
#38500000
0#
#39000000
1#
#39500000
0#
#40000000
1#
b1010 %
#40500000
0#
#41000000
1#
#41500000
0#
#42000000
1#
#42500000
0#
#43000000
1#
#43500000
0#
#44000000
1#
b1011 %
#44500000
0#
#45000000
1#
#45500000
0#
#46000000
1#
#46500000
0#
#47000000
1#
#47500000
0#
#48000000
1#
b1100 %
#48500000
0#
#49000000
1#
#49500000
0#
#50000000
0"
1#
