source/dsp/multiplier/multiplier.vhd
library ieee;
    use ieee.std_logic_1164.all;
    use ieee.numeric_std.all;

library work;
    use work.multiplier_pkg.all;

entity multiplier is
    port (
        multiplier_clocks : in multiplier_clock_group;

        multiplier_data_in : in multiplier_data_input_group;
        multiplier_data_out : out multiplier_data_output_group
    );
end entity;

architecture rtl of multiplier is


    signal mult_result : result_array(0 to 1);
    signal mult_a, mult_b : sign_array(0 to 1);

begin

    test_multiplier : process(multiplier_clocks.dsp_clock)

        variable multiplier_counter : integer range 0 to 7; 
    begin
        if rising_edge(multiplier_clocks.dsp_clock) then

            mult_a(0) <= to_signed(multiplier_data_in.mult_a,18);
            mult_b(0) <= to_signed(multiplier_data_in.mult_b,18);
            -- mult_result(0) <= mult_a(0) * mult_b(0);

            multiplier_data_out.multiplier_result <= mult_a(0) * mult_b(0);

            multiplier_data_out.multiplier_is_ready <= false;
            CASE multiplier_counter is
                WHEN 0 =>
                    if multiplier_data_in.multiplication_is_requested then
                        multiplier_counter := multiplier_counter + 1;
                    end if;
                WHEN 1 => 
                        multiplier_counter := multiplier_counter + 1;
                WHEN 2 => 
                    multiplier_data_out.multiplier_is_ready <= true;
                    multiplier_counter := 0;
                WHEN others =>
                    multiplier_counter := 0;
            end CASE;
        end if; --rising_edge
    end process test_multiplier;	

end rtl;

source/dsp/multiplier/simulation/tb_multiplier.vhd
LIBRARY ieee  ; 
LIBRARY std  ; 
    USE ieee.NUMERIC_STD.all  ; 
    USE ieee.std_logic_1164.all  ; 
    USE ieee.std_logic_textio.all  ; 
    use ieee.math_real.all;
    USE std.textio.all  ; 

library work;
    use work.multiplier_pkg.all;

entity tb_multiplier is
end;

architecture sim of tb_multiplier is
    signal rstn : std_logic;

    signal simulation_running : boolean;
    signal simulator_clock : std_logic;
    constant clock_per : time := 1 ns;
    constant clock_half_per : time := 0.5 ns;
    constant simtime_in_clocks : integer := 200;

    signal multiplier_clocks   : multiplier_clock_group;
    signal multiplier_data_in  : multiplier_data_input_group;
    signal multiplier_data_out :  multiplier_data_output_group;
    signal mpy_test : sign36;
    signal testcounter : integer;
    signal signal_counter : int18;
    signal jihuu_y : int18;
    signal if1_thenmultisrunning : int18;

begin

    simtime : process
    begin
        simulation_running <= true;
        wait for simtime_in_clocks*clock_per;
        simulation_running <= false;
        wait;
    end process simtime;	


    sim_clock_gen : process
    begin
        simulator_clock <= '0';
        rstn <= '0';
        simulator_clock <= '0';
        wait for clock_half_per;
        while simulation_running loop
            wait for clock_half_per;
                rstn <= '1';
                simulator_clock <= not simulator_clock;
            end loop;
        wait;
    end process;

    multiplier_clocks.dsp_clock <= simulator_clock;
    u_multiplier : multiplier
        port map(
            multiplier_clocks, 
            multiplier_data_in,
            multiplier_data_out 
        );

    test_multiplier : process(simulator_clock, rstn)

        constant b0 : int18 := 9e3;
        constant a0 : int18 := 20e3;
        constant b1 : int18 := 2**15-1-b0-a0;
        constant uin : int18 := 15384;
        variable mem1, y : int18;
        variable a, b: int18;
        variable mpy_result : sign36;
        variable process_counter : int18;
        variable plaaplaa :int18;
        ------------------------------------------------------------------------
        impure function "*" (left, right : int18) return sign36
        is
            variable result : sign36;
        begin
            alu_mpy(left, right, result, multiplier_data_in, multiplier_data_out);
            return result;
        end "*";
        ------------------------------------------------------------------------
    begin
        if rstn = '0' then
        -- reset state
            a := 16;
            b := 16;
            mpy_test <= (others => '0');
            process_counter := 0;
            mem1 := 0;
            y := 0;
            signal_counter <= process_counter;
            process_counter := 0;
            jihuu_y <= 0;

        elsif rising_edge(simulator_clock) then
            signal_counter <= process_counter;
            testcounter <= process_counter;
            mpy_test <=multiplier_data_out.multiplier_result; 

            multiplier_data_in.multiplication_is_requested <= false;

            if multiplier_is_ready(multiplier_data_out) then
                if1_thenmultisrunning <= 1;
            else
                if1_thenmultisrunning <= 0;
            end if;

            case process_counter is
                WHEN 0 => 
                    mpy_result := 2**15 * 15;
                    if multiplier_is_ready(multiplier_data_out) then
                        jihuu_y <= get_result(multiplier_data_out,0);
                        increment(process_counter);
                    end if;
                WHEN 1 => 
                    mpy_result := 2**15 * 16;
                    if multiplier_is_ready(multiplier_data_out) then
                        jihuu_y <= get_result(multiplier_data_out,0);
                        increment(process_counter);
                    end if;
                WHEN 2 => 
                    mpy_result := 2**15 * 17;
                    if multiplier_is_ready(multiplier_data_out) then
                        jihuu_y <= get_result(multiplier_data_out,0);
                        increment(process_counter);
                    end if;
                when 3 =>
                    mpy_result := 2**15 * 18;
                    if multiplier_is_ready(multiplier_data_out) then
                        jihuu_y <= get_result(multiplier_data_out,0);
                        increment(process_counter);
                    end if;
                when others =>
            end CASE;

        end if; -- rstn
    end process test_multiplier;	

end sim;

source/dsp/multiplier/simulation/tb_multiplier.vcd
$date
  Sun Jan 19 14:31:59 2020
$end
$version
  GHDL v0
$end
$timescale
  1 fs
$end
$scope module standard $end
$upscope $end
$scope module std_logic_1164 $end
$upscope $end
$scope module numeric_std $end
$upscope $end
$scope module textio $end
$upscope $end
$scope module std_logic_textio $end
$upscope $end
$scope module math_real $end
$upscope $end
$scope module multiplier_pkg $end
$upscope $end
$scope module tb_multiplier $end
$var reg 1 ! rstn $end
$var reg 1 " simulation_running $end
$var reg 1 # simulator_clock $end
$comment multiplier_clocks is not handled $end
$comment multiplier_data_in is not handled $end
$comment multiplier_data_out is not handled $end
$var reg 36 $ mpy_test[35:0] $end
$var integer 32 % testcounter $end
$var integer 32 & signal_counter $end
$var integer 32 ' jihuu_y $end
$var integer 32 ( if1_thenmultisrunning $end
$scope module u_multiplier $end
$comment multiplier_clocks is not handled $end
$comment multiplier_data_in is not handled $end
$comment multiplier_data_out is not handled $end
$comment mult_result is not handled $end
$comment mult_a is not handled $end
$comment mult_b is not handled $end
$upscope $end
$upscope $end
$enddefinitions $end
#0
0!
1"
0#
b000000000000000000000000000000000000 $
b10000000000000000000000000000000 %
b0 &
b0 '
b11111111111111100000000000000000 (
#500000
#1000000
1!
1#
bUUUUUUUUUUUUUUUUUUUUUUUUUUUUUUUUUUUU $
b0 %
b0 (
#1500000
0#
#2000000
1#
bXXXXXXXXXXXXXXXXXXXXXXXXXXXXXXXXXXXX $
#2500000
0#
#3000000
1#
b000000000000000001111000000000000000 $
#3500000
0#
#4000000
1#
b1000 '
b1 (
#4500000
0#
#5000000
1#
b1 %
b1 &
b0 (
#5500000
0#
#6000000
1#
#6500000
0#
#7000000
1#
b000000000000000010000000000000000000 $
#7500000
0#
#8000000
1#
b1 (
#8500000
0#
#9000000
1#
b10 %
b10 &
b0 (
#9500000
0#
#10000000
1#
#10500000
0#
#11000000
1#
b000000000000000010001000000000000000 $
#11500000
0#
#12000000
1#
b1001 '
b1 (
#12500000
0#
#13000000
1#
b11 %
b11 &
b0 (
#13500000
0#
#14000000
1#
#14500000
0#
#15000000
1#
b000000000000000010010000000000000000 $
#15500000
0#
#16000000
1#
b1 (
#16500000
0#
#17000000
1#
b100 %
b100 &
b0 (
