source/dsp/multiplier/multiplier.vhd
library ieee;
    use ieee.std_logic_1164.all;
    use ieee.numeric_std.all;

    use work.multiplier_entity_pkg.all;

entity multiplier is
    port (
        multiplier_clocks : in multiplier_clock_group;

        multiplier_data_in : in multiplier_data_input_group;
        multiplier_data_out : out multiplier_data_output_group
    );
end entity;

architecture rtl of multiplier is


    signal mult_result : result_array(0 to 0);
    signal mult_a, mult_b : sign_array(0 to 1);
    component multiplier_18x18 IS
	PORT
	(
		clock		: IN STD_LOGIC ;
		dataa		: IN STD_LOGIC_VECTOR (17 DOWNTO 0);
		datab		: IN STD_LOGIC_VECTOR (17 DOWNTO 0);
		result		: OUT STD_LOGIC_VECTOR (35 DOWNTO 0)
	);
    END component;

	signal dataa		: STD_LOGIC_VECTOR (17 DOWNTO 0);
	signal datab		: STD_LOGIC_VECTOR (17 DOWNTO 0);
	signal result		:  STD_LOGIC_VECTOR (35 DOWNTO 0);

    signal multiplier_counter : natural range 0 to 9; 

begin

    test_multiplier : process(multiplier_clocks.dsp_clock)

    begin
        if rising_edge(multiplier_clocks.dsp_clock) then

            mult_a(0) <= to_signed(multiplier_data_in.mult_a,18);
            mult_b(0) <= to_signed(multiplier_data_in.mult_b,18);
            multiplier_data_out.multiplier_result <= mult_a(0) * mult_b(0);


            if multiplier_data_in.multiplication_is_requested then
                multiplier_counter <= 3;
            end if;

            if multiplier_counter > 0 then
                multiplier_counter <= multiplier_counter - 1;
            end if;

            multiplier_data_out.multiplier_is_ready <= false;
            if multiplier_counter = 1 then
                multiplier_data_out.multiplier_is_ready <= true;
            end if;

        end if; --rising_edge
    end process test_multiplier;	

end rtl;

source/dsp/multiplier/simulation/tb_multiplier.vhd
LIBRARY ieee  ; 
LIBRARY std  ; 
    USE ieee.NUMERIC_STD.all  ; 
    USE ieee.std_logic_1164.all  ; 
    USE ieee.std_logic_textio.all  ; 
    use ieee.math_real.all;
    USE std.textio.all  ; 

library work;
    use work.multiplier_pkg.all;

entity tb_multiplier is
end;

architecture sim of tb_multiplier is
    signal rstn : std_logic;

    signal simulation_running : boolean;
    signal simulator_clock : std_logic;
    constant clock_per : time := 1 ns;
    constant clock_half_per : time := 0.5 ns;
    constant simtime_in_clocks : integer := 200;

    signal multiplier_clocks   : multiplier_clock_group;
    signal multiplier_data_in  : multiplier_data_input_group;
    signal multiplier_data_out :  multiplier_data_output_group;
    signal mpy_test : sign36;
    signal testcounter : integer;
    signal signal_counter : int18;
    signal jihuu_y : int18;

begin

    simtime : process
    begin
        simulation_running <= true;
        wait for simtime_in_clocks*clock_per;
        simulation_running <= false;
        wait;
    end process simtime;	


    sim_clock_gen : process
    begin
        simulator_clock <= '0';
        rstn <= '0';
        simulator_clock <= '0';
        wait for clock_half_per;
        while simulation_running loop
            wait for clock_half_per;
                rstn <= '1';
                simulator_clock <= not simulator_clock;
            end loop;
        wait;
    end process;

    multiplier_clocks.dsp_clock <= simulator_clock;
    u_multiplier : multiplier
        port map(
            multiplier_clocks, 
            multiplier_data_in,
            multiplier_data_out 
        );

    test_multiplier : process(simulator_clock, rstn)

        constant b1 : int18 := 3800;
        constant a1 : int18 := 18e3;
        constant b0 : int18 := 2**15-a1-b1;
        constant uin : int18 := 10e3;
        variable mem1, mem2, y : int18;
        variable a, b: int18;
        variable mpy_result : sign36;
        variable process_counter : int18;
        variable plaaplaa :int18;
        variable radix : int18;
        ------------------------------------------------------------------------
        impure function "*" (left, right : int18) return int18
        is
            variable result : sign36;
        begin
            alu_mpy(left, right, result, multiplier_data_in, multiplier_data_out);
            return get_result(multiplier_data_out,radix);
        end "*";
        ------------------------------------------------------------------------
    begin
        if rstn = '0' then
        -- reset state
            a := 16;
            b := 16;
            mpy_test <= (others => '0');
            process_counter := 0;
            mem1 := 0;
            y := 0;
            signal_counter <= process_counter;
            process_counter := 0;
            jihuu_y <= 0;
            radix := 0;

        elsif rising_edge(simulator_clock) then
            signal_counter <= process_counter;
            testcounter <= process_counter;
            mpy_test <=multiplier_data_out.multiplier_result; 

            multiplier_data_in.multiplication_is_requested <= false;

            radix := -1;
            case process_counter is
                WHEN 0 => 
                    y := uin * b0 + mem1;
                    if multiplier_is_ready(multiplier_data_out) then
                        increment(process_counter);
                        jihuu_y <= y;
                    end if;
                WHEN 1 => 
                    mem1 := b1 * uin;
                    increment(process_counter);
                WHEN 2 => 
                    mem1 := a1 * y;
                    increment(process_counter);
                when 3 =>
                    mem1 := get_result(multiplier_data_out,radix);
                    increment(process_counter);
                when 4 =>
                    mem1 := mem1 + get_result(multiplier_data_out,radix);
                    process_counter := 0;
                when others =>
            end CASE;

        end if; -- rstn
    end process test_multiplier;	

end sim;

source/dsp/multiplier/simulation/tb_multiplier.vcd
$date
  Sun Jan 19 16:06:00 2020
$end
$version
  GHDL v0
$end
$timescale
  1 fs
$end
$scope module standard $end
$upscope $end
$scope module std_logic_1164 $end
$upscope $end
$scope module numeric_std $end
$upscope $end
$scope module textio $end
$upscope $end
$scope module std_logic_textio $end
$upscope $end
$scope module math_real $end
$upscope $end
$scope module multiplier_pkg $end
$upscope $end
$scope module tb_multiplier $end
$var reg 1 ! rstn $end
$var reg 1 " simulation_running $end
$var reg 1 # simulator_clock $end
$comment multiplier_clocks is not handled $end
$comment multiplier_data_in is not handled $end
$comment multiplier_data_out is not handled $end
$var reg 36 $ mpy_test[35:0] $end
$var integer 32 % testcounter $end
$var integer 32 & signal_counter $end
$var integer 32 ' jihuu_y $end
$scope module u_multiplier $end
$comment multiplier_clocks is not handled $end
$comment multiplier_data_in is not handled $end
$comment multiplier_data_out is not handled $end
$comment mult_result is not handled $end
$comment mult_a is not handled $end
$comment mult_b is not handled $end
$upscope $end
$upscope $end
$enddefinitions $end
#0
0!
1"
0#
b000000000000000000000000000000000000 $
b10000000000000000000000000000000 %
b0 &
b0 '
#500000
#1000000
1!
1#
bUUUUUUUUUUUUUUUUUUUUUUUUUUUUUUUUUUUU $
b0 %
#1500000
0#
#2000000
1#
bXXXXXXXXXXXXXXXXXXXXXXXXXXXXXXXXXXXX $
#2500000
0#
#3000000
1#
b000000000110100010011001010110000000 $
b110100010011 '
#3500000
0#
#4000000
1#
b1 %
b1 &
#4500000
0#
#5000000
1#
b10 %
b10 &
#5500000
0#
#6000000
1#
b000000000010010000111101010110000000 $
b11 %
b11 &
#6500000
0#
#7000000
1#
b000000000011100101110100011111110000 $
b100 %
b100 &
#7500000
0#
#8000000
1#
b0 %
b0 &
#8500000
0#
#9000000
1#
#9500000
0#
#10000000
1#
b000000000110100010011001010110000000 $
b1100011001010 '
#10500000
0#
#11000000
1#
b1 %
b1 &
#11500000
0#
#12000000
1#
b10 %
b10 &
#12500000
0#
#13000000
1#
b000000000010010000111101010110000000 $
b11 %
b11 &
#13500000
0#
#14000000
1#
b000000000110110011101111101100100000 $
b100 %
b100 &
#14500000
0#
#15000000
1#
b0 %
b0 &
#15500000
0#
#16000000
1#
#16500000
0#
#17000000
1#
b000000000110100010011001010110000000 $
b1111100111001 '
#17500000
0#
#18000000
1#
b1 %
b1 &
#18500000
0#
#19000000
1#
b10 %
b10 &
#19500000
0#
#20000000
1#
b000000000010010000111101010110000000 $
b11 %
b11 &
#20500000
0#
#21000000
1#
b000000001000100100110101011111010000 $
b100 %
b100 &
#21500000
0#
#22000000
1#
b0 %
b0 &
#22500000
0#
#23000000
1#
#23500000
0#
#24000000
1#
b000000000110100010011001010110000000 $
b10001011000010 '
#24500000
0#
#25000000
1#
b1 %
b1 &
#25500000
0#
#26000000
1#
b10 %
b10 &
#26500000
0#
#27000000
1#
b000000000010010000111101010110000000 $
b11 %
b11 &
#27500000
0#
#28000000
1#
b000000001001100010111110100010100000 $
b100 %
b100 &
#28500000
0#
#29000000
1#
b0 %
b0 &
#29500000
0#
#30000000
1#
#30500000
0#
#31000000
1#
b000000000110100010011001010110000000 $
b10010010110011 '
#31500000
0#
#32000000
1#
b1 %
b1 &
#32500000
0#
#33000000
1#
b10 %
b10 &
#33500000
0#
#34000000
1#
b000000000010010000111101010110000000 $
b11 %
b11 &
#34500000
0#
#35000000
1#
b000000001010000101000110100111110000 $
b100 %
b100 &
#35500000
0#
#36000000
1#
b0 %
b0 &
#36500000
0#
#37000000
1#
#37500000
0#
#38000000
1#
b000000000110100010011001010110000000 $
b10010111000100 '
#38500000
0#
#39000000
1#
b1 %
b1 &
#39500000
0#
#40000000
1#
b10 %
b10 &
#40500000
0#
#41000000
1#
b000000000010010000111101010110000000 $
b11 %
b11 &
#41500000
0#
#42000000
1#
b000000001010010111110110010101000000 $
b100 %
b100 &
#42500000
0#
#43000000
1#
b0 %
b0 &
#43500000
0#
#44000000
1#
#44500000
0#
#45000000
1#
b000000000110100010011001010110000000 $
b10011001011010 '
#45500000
0#
#46000000
1#
b1 %
b1 &
#46500000
0#
#47000000
1#
b10 %
b10 &
#47500000
0#
#48000000
1#
b000000000010010000111101010110000000 $
b11 %
b11 &
#48500000
0#
#49000000
1#
b000000001010100010001001100000100000 $
b100 %
b100 &
#49500000
0#
#50000000
1#
b0 %
b0 &
#50500000
0#
#51000000
1#
#51500000
0#
#52000000
1#
b000000000110100010011001010110000000 $
b10011010101100 '
#52500000
0#
#53000000
1#
b1 %
b1 &
#53500000
0#
#54000000
1#
b10 %
b10 &
#54500000
0#
#55000000
1#
b000000000010010000111101010110000000 $
b11 %
b11 &
#55500000
0#
#56000000
1#
b000000001010100111110001110111000000 $
b100 %
b100 &
#56500000
0#
#57000000
1#
b0 %
b0 &
#57500000
0#
#58000000
1#
#58500000
0#
#59000000
1#
b000000000110100010011001010110000000 $
b10011011011001 '
#59500000
0#
#60000000
1#
b1 %
b1 &
#60500000
0#
#61000000
1#
b10 %
b10 &
#61500000
0#
#62000000
1#
b000000000010010000111101010110000000 $
b11 %
b11 &
#62500000
0#
#63000000
1#
b000000001010101010110111100111010000 $
b100 %
b100 &
#63500000
0#
#64000000
1#
b0 %
b0 &
#64500000
0#
#65000000
1#
#65500000
0#
#66000000
1#
b000000000110100010011001010110000000 $
b10011011110010 '
#66500000
0#
#67000000
1#
b1 %
b1 &
#67500000
0#
#68000000
1#
b10 %
b10 &
#68500000
0#
#69000000
1#
b000000000010010000111101010110000000 $
b11 %
b11 &
#69500000
0#
#70000000
1#
b000000001010101100100101011110100000 $
b100 %
b100 &
#70500000
0#
#71000000
1#
b0 %
b0 &
#71500000
0#
#72000000
1#
#72500000
0#
#73000000
1#
b000000000110100010011001010110000000 $
b10011100000000 '
#73500000
0#
#74000000
1#
b1 %
b1 &
#74500000
0#
#75000000
1#
b10 %
b10 &
#75500000
0#
#76000000
1#
b000000000010010000111101010110000000 $
b11 %
b11 &
#76500000
0#
#77000000
1#
b000000001010101101100011000000000000 $
b100 %
b100 &
#77500000
0#
#78000000
1#
b0 %
b0 &
#78500000
0#
#79000000
1#
#79500000
0#
#80000000
1#
b000000000110100010011001010110000000 $
b10011100000111 '
#80500000
0#
#81000000
1#
b1 %
b1 &
#81500000
0#
#82000000
1#
b10 %
b10 &
#82500000
0#
#83000000
1#
b000000000010010000111101010110000000 $
b11 %
b11 &
#83500000
0#
#84000000
1#
b000000001010101110000001110000110000 $
b100 %
b100 &
#84500000
0#
#85000000
1#
b0 %
b0 &
#85500000
0#
#86000000
1#
#86500000
0#
#87000000
1#
b000000000110100010011001010110000000 $
b10011100001011 '
#87500000
0#
#88000000
1#
b1 %
b1 &
#88500000
0#
#89000000
1#
b10 %
b10 &
#89500000
0#
#90000000
1#
b000000000010010000111101010110000000 $
b11 %
b11 &
#90500000
0#
#91000000
1#
b000000001010101110010011010101110000 $
b100 %
b100 &
#91500000
0#
#92000000
1#
b0 %
b0 &
#92500000
0#
#93000000
1#
#93500000
0#
#94000000
1#
b000000000110100010011001010110000000 $
b10011100001101 '
#94500000
0#
#95000000
1#
b1 %
b1 &
#95500000
0#
#96000000
1#
b10 %
b10 &
#96500000
0#
#97000000
1#
b000000000010010000111101010110000000 $
b11 %
b11 &
#97500000
0#
#98000000
1#
b000000001010101110011100001000010000 $
b100 %
b100 &
#98500000
0#
#99000000
1#
b0 %
b0 &
#99500000
0#
#100000000
1#
#100500000
0#
#101000000
1#
b000000000110100010011001010110000000 $
b10011100001111 '
#101500000
0#
#102000000
1#
b1 %
b1 &
#102500000
0#
#103000000
1#
b10 %
b10 &
#103500000
0#
#104000000
1#
b000000000010010000111101010110000000 $
b11 %
b11 &
#104500000
0#
#105000000
1#
b000000001010101110100100111010110000 $
b100 %
b100 &
#105500000
0#
#106000000
1#
b0 %
b0 &
#106500000
0#
#107000000
1#
#107500000
0#
#108000000
1#
b000000000110100010011001010110000000 $
b10011100010000 '
#108500000
0#
#109000000
1#
b1 %
b1 &
#109500000
0#
#110000000
1#
b10 %
b10 &
#110500000
0#
#111000000
1#
b000000000010010000111101010110000000 $
b11 %
b11 &
#111500000
0#
#112000000
1#
b000000001010101110101001010100000000 $
b100 %
b100 &
#112500000
0#
#113000000
1#
b0 %
b0 &
#113500000
0#
#114000000
1#
#114500000
0#
#115000000
1#
b000000000110100010011001010110000000 $
#115500000
0#
#116000000
1#
b1 %
b1 &
#116500000
0#
#117000000
1#
b10 %
b10 &
#117500000
0#
#118000000
1#
b000000000010010000111101010110000000 $
b11 %
b11 &
#118500000
0#
#119000000
1#
b000000001010101110101001010100000000 $
b100 %
b100 &
#119500000
0#
#120000000
1#
b0 %
b0 &
#120500000
0#
#121000000
1#
#121500000
0#
#122000000
1#
b000000000110100010011001010110000000 $
#122500000
0#
#123000000
1#
b1 %
b1 &
#123500000
0#
#124000000
1#
b10 %
b10 &
#124500000
0#
#125000000
1#
b000000000010010000111101010110000000 $
b11 %
b11 &
#125500000
0#
#126000000
1#
b000000001010101110101001010100000000 $
b100 %
b100 &
#126500000
0#
#127000000
1#
b0 %
b0 &
#127500000
0#
#128000000
1#
#128500000
0#
#129000000
1#
b000000000110100010011001010110000000 $
#129500000
0#
#130000000
1#
b1 %
b1 &
#130500000
0#
#131000000
1#
b10 %
b10 &
#131500000
0#
#132000000
1#
b000000000010010000111101010110000000 $
b11 %
b11 &
#132500000
0#
#133000000
1#
b000000001010101110101001010100000000 $
b100 %
b100 &
#133500000
0#
#134000000
1#
b0 %
b0 &
#134500000
0#
#135000000
1#
#135500000
0#
#136000000
1#
b000000000110100010011001010110000000 $
#136500000
0#
#137000000
1#
b1 %
b1 &
#137500000
0#
#138000000
1#
b10 %
b10 &
#138500000
0#
#139000000
1#
b000000000010010000111101010110000000 $
b11 %
b11 &
#139500000
0#
#140000000
1#
b000000001010101110101001010100000000 $
b100 %
b100 &
#140500000
0#
#141000000
1#
b0 %
b0 &
#141500000
0#
#142000000
1#
#142500000
0#
#143000000
1#
b000000000110100010011001010110000000 $
#143500000
0#
#144000000
1#
b1 %
b1 &
#144500000
0#
#145000000
1#
b10 %
b10 &
#145500000
0#
#146000000
1#
b000000000010010000111101010110000000 $
b11 %
b11 &
#146500000
0#
#147000000
1#
b000000001010101110101001010100000000 $
b100 %
b100 &
#147500000
0#
#148000000
1#
b0 %
b0 &
#148500000
0#
#149000000
1#
#149500000
0#
#150000000
1#
b000000000110100010011001010110000000 $
#150500000
0#
#151000000
1#
b1 %
b1 &
#151500000
0#
#152000000
1#
b10 %
b10 &
#152500000
0#
#153000000
1#
b000000000010010000111101010110000000 $
b11 %
b11 &
#153500000
0#
#154000000
1#
b000000001010101110101001010100000000 $
b100 %
b100 &
#154500000
0#
#155000000
1#
b0 %
b0 &
#155500000
0#
#156000000
1#
#156500000
0#
#157000000
1#
b000000000110100010011001010110000000 $
#157500000
0#
#158000000
1#
b1 %
b1 &
#158500000
0#
#159000000
1#
b10 %
b10 &
#159500000
0#
#160000000
1#
b000000000010010000111101010110000000 $
b11 %
b11 &
#160500000
0#
#161000000
1#
b000000001010101110101001010100000000 $
b100 %
b100 &
#161500000
0#
#162000000
1#
b0 %
b0 &
#162500000
0#
#163000000
1#
#163500000
0#
#164000000
1#
b000000000110100010011001010110000000 $
#164500000
0#
#165000000
1#
b1 %
b1 &
#165500000
0#
#166000000
1#
b10 %
b10 &
#166500000
0#
#167000000
1#
b000000000010010000111101010110000000 $
b11 %
b11 &
#167500000
0#
#168000000
1#
b000000001010101110101001010100000000 $
b100 %
b100 &
#168500000
0#
#169000000
1#
b0 %
b0 &
#169500000
0#
#170000000
1#
#170500000
0#
#171000000
1#
b000000000110100010011001010110000000 $
#171500000
0#
#172000000
1#
b1 %
b1 &
#172500000
0#
#173000000
1#
b10 %
b10 &
#173500000
0#
#174000000
1#
b000000000010010000111101010110000000 $
b11 %
b11 &
#174500000
0#
#175000000
1#
b000000001010101110101001010100000000 $
b100 %
b100 &
#175500000
0#
#176000000
1#
b0 %
b0 &
#176500000
0#
#177000000
1#
#177500000
0#
#178000000
1#
b000000000110100010011001010110000000 $
#178500000
0#
#179000000
1#
b1 %
b1 &
#179500000
0#
#180000000
1#
b10 %
b10 &
#180500000
0#
#181000000
1#
b000000000010010000111101010110000000 $
b11 %
b11 &
#181500000
0#
#182000000
1#
b000000001010101110101001010100000000 $
b100 %
b100 &
#182500000
0#
#183000000
1#
b0 %
b0 &
#183500000
0#
#184000000
1#
#184500000
0#
#185000000
1#
b000000000110100010011001010110000000 $
#185500000
0#
#186000000
1#
b1 %
b1 &
#186500000
0#
#187000000
1#
b10 %
b10 &
#187500000
0#
#188000000
1#
b000000000010010000111101010110000000 $
b11 %
b11 &
#188500000
0#
#189000000
1#
b000000001010101110101001010100000000 $
b100 %
b100 &
#189500000
0#
#190000000
1#
b0 %
b0 &
#190500000
0#
#191000000
1#
#191500000
0#
#192000000
1#
b000000000110100010011001010110000000 $
#192500000
0#
#193000000
1#
b1 %
b1 &
#193500000
0#
#194000000
1#
b10 %
b10 &
#194500000
0#
#195000000
1#
b000000000010010000111101010110000000 $
b11 %
b11 &
#195500000
0#
#196000000
1#
b000000001010101110101001010100000000 $
b100 %
b100 &
#196500000
0#
#197000000
1#
b0 %
b0 &
#197500000
0#
#198000000
1#
#198500000
0#
#199000000
1#
b000000000110100010011001010110000000 $
#199500000
0#
#200000000
0"
1#
b1 %
b1 &
